LICENSE
MANIFEST.in
README.rst
setup.py
dosca/__init__.py
dosca/dosca.py
dosca/ext.py
dosca.egg-info/PKG-INFO
dosca.egg-info/SOURCES.txt
dosca.egg-info/dependency_links.txt
dosca.egg-info/top_level.txt