Metadata-Version: 1.1
Name: dosca
Version: 1.8.0
Summary: Damn Simple Config File Parser.
Home-page: https://github.com/little-arhat/dosca
Author: Roma Sokolov
Author-email: sokolov.r.v@gmail.com
License: MIT
Platform: UNKNOWN
Classifier: Natural Language :: English
Classifier: License :: OSI Approved :: MIT License
Classifier: Programming Language :: Python
Classifier: Programming Language :: Python :: 2.6
Classifier: Programming Language :: Python :: 2.7
Classifier: Programming Language :: Python :: 3
